sfsidb
