Metadata-Version: 2.1
Name: sfsidb
Version: 0.1.6
Summary: This package provides tools to view engineering databases
Home-page: UNKNOWN
Author: Maxim Millen
Author-email: mmi46@uclive.ac.nz
License: MIT
Platform: UNKNOWN
Classifier: Development Status :: 3 - Alpha
Classifier: Intended Audience :: Science/Research
Classifier: Topic :: Scientific/Engineering
Classifier: License :: OSI Approved :: MIT License
Classifier: Programming Language :: Python :: 3
Requires-Python: >=3
Provides-Extra: test
